finterion/__init__.py
finterion/configuration/__init__.py
finterion/configuration/urls.py
finterion/exceptions.py
finterion/finterion.py
finterion/models/__init__.py
finterion/models/algorithm.py
finterion/models/algorithm_profile.py
finterion/models/model.py
finterion/models/order.py
finterion/models/order_side.py
finterion/models/order_status.py
finterion/models/order_type.py
finterion/models/portfolio.py
finterion/models/position.py
finterion/services.py
finterion-0.8.8.dist-info/LICENSE
finterion-0.8.8.dist-info/METADATA
finterion-0.8.8.dist-info/WHEEL
finterion-0.8.8.dist-info/RECORD
